decoratorium.py
decoratorium-2.0.dist-info/DESCRIPTION.rst
decoratorium-2.0.dist-info/METADATA
decoratorium-2.0.dist-info/RECORD
decoratorium-2.0.dist-info/WHEEL
decoratorium-2.0.dist-info/metadata.json
decoratorium-2.0.dist-info/top_level.txt
