Metadata-Version: 2.0
Name: decoratorium
Version: 2.0
Summary: Decorator class implementation.
Home-page: https://github.com/lig/decoratorium
Author: Serge Matveenko
Author-email: s@matveenko.ru
License: MIT
Keywords: python decorator class klass
Platform: UNKNOWN
Classifier: Development Status :: 5 - Production/Stable
Classifier: Intended Audience :: Developers
Classifier: Topic :: Software Development :: Libraries
Classifier: License :: OSI Approved :: MIT License
Classifier: Programming Language :: Python :: 3
Classifier: Programming Language :: Python :: 3 :: Only
Requires-Dist: decorator
Provides-Extra: test
Requires-Dist: pytest; extra == 'test'
